{"nodes": [{"id": "c_users_gtrip_onedrive_desktop_current_frontend_src_app_jsx", "label": "App.jsx", "file_type": "code", "source_file": "C:\\Users\\gtrip\\OneDrive\\Desktop\\current\\frontend\\src\\App.jsx", "source_location": "L1"}, {"id": "app_errorboundary", "label": "ErrorBoundary", "file_type": "code", "source_file": "C:\\Users\\gtrip\\OneDrive\\Desktop\\current\\frontend\\src\\App.jsx", "source_location": "L21"}, {"id": "app_errorboundary_constructor", "label": ".constructor()", "file_type": "code", "source_file": "C:\\Users\\gtrip\\OneDrive\\Desktop\\current\\frontend\\src\\App.jsx", "source_location": "L22"}, {"id": "app_errorboundary_getderivedstatefromerror", "label": ".getDerivedStateFromError()", "file_type": "code", "source_file": "C:\\Users\\gtrip\\OneDrive\\Desktop\\current\\frontend\\src\\App.jsx", "source_location": "L23"}, {"id": "app_errorboundary_render", "label": ".render()", "file_type": "code", "source_file": "C:\\Users\\gtrip\\OneDrive\\Desktop\\current\\frontend\\src\\App.jsx", "source_location": "L24"}, {"id": "app_comingsoonnavitem", "label": "ComingSoonNavItem()", "file_type": "code", "source_file": "C:\\Users\\gtrip\\OneDrive\\Desktop\\current\\frontend\\src\\App.jsx", "source_location": "L39"}, {"id": "app_authmodal", "label": "AuthModal()", "file_type": "code", "source_file": "C:\\Users\\gtrip\\OneDrive\\Desktop\\current\\frontend\\src\\App.jsx", "source_location": "L52"}, {"id": "app_useravatar", "label": "UserAvatar()", "file_type": "code", "source_file": "C:\\Users\\gtrip\\OneDrive\\Desktop\\current\\frontend\\src\\App.jsx", "source_location": "L90"}, {"id": "app_usermenu", "label": "UserMenu()", "file_type": "code", "source_file": "C:\\Users\\gtrip\\OneDrive\\Desktop\\current\\frontend\\src\\App.jsx", "source_location": "L102"}, {"id": "app_publiclanding", "label": "PublicLanding()", "file_type": "code", "source_file": "C:\\Users\\gtrip\\OneDrive\\Desktop\\current\\frontend\\src\\App.jsx", "source_location": "L126"}, {"id": "app_authenticatedapp", "label": "AuthenticatedApp()", "file_type": "code", "source_file": "C:\\Users\\gtrip\\OneDrive\\Desktop\\current\\frontend\\src\\App.jsx", "source_location": "L187"}, {"id": "app_app", "label": "App()", "file_type": "code", "source_file": "C:\\Users\\gtrip\\OneDrive\\Desktop\\current\\frontend\\src\\App.jsx", "source_location": "L418"}], "edges": [{"source": "c_users_gtrip_onedrive_desktop_current_frontend_src_app_jsx", "target": "react", "relation": "imports_from", "confidence": "EXTRACTED", "source_file": "C:\\Users\\gtrip\\OneDrive\\Desktop\\current\\frontend\\src\\App.jsx", "source_location": "L1", "weight": 1.0}, {"source": "c_users_gtrip_onedrive_desktop_current_frontend_src_app_jsx", "target": "lucide_react", "relation": "imports_from", "confidence": "EXTRACTED", "source_file": "C:\\Users\\gtrip\\OneDrive\\Desktop\\current\\frontend\\src\\App.jsx", "source_location": "L2", "weight": 1.0}, {"source": "c_users_gtrip_onedrive_desktop_current_frontend_src_app_jsx", "target": "c_users_gtrip_onedrive_desktop_current_frontend_src_components_applogic", "relation": "imports_from", "confidence": "EXTRACTED", "source_file": "C:\\Users\\gtrip\\OneDrive\\Desktop\\current\\frontend\\src\\App.jsx", "source_location": "L7", "weight": 1.0}, {"source": "c_users_gtrip_onedrive_desktop_current_frontend_src_app_jsx", "target": "c_users_gtrip_onedrive_desktop_current_frontend_src_components_uihelpers", "relation": "imports_from", "confidence": "EXTRACTED", "source_file": "C:\\Users\\gtrip\\OneDrive\\Desktop\\current\\frontend\\src\\App.jsx", "source_location": "L8", "weight": 1.0}, {"source": "c_users_gtrip_onedrive_desktop_current_frontend_src_app_jsx", "target": "c_users_gtrip_onedrive_desktop_current_frontend_src_components_landingview", "relation": "imports_from", "confidence": "EXTRACTED", "source_file": "C:\\Users\\gtrip\\OneDrive\\Desktop\\current\\frontend\\src\\App.jsx", "source_location": "L9", "weight": 1.0}, {"source": "c_users_gtrip_onedrive_desktop_current_frontend_src_app_jsx", "target": "c_users_gtrip_onedrive_desktop_current_frontend_src_components_uploadview", "relation": "imports_from", "confidence": "EXTRACTED", "source_file": "C:\\Users\\gtrip\\OneDrive\\Desktop\\current\\frontend\\src\\App.jsx", "source_location": "L10", "weight": 1.0}, {"source": "c_users_gtrip_onedrive_desktop_current_frontend_src_app_jsx", "target": "c_users_gtrip_onedrive_desktop_current_frontend_src_components_resultsview", "relation": "imports_from", "confidence": "EXTRACTED", "source_file": "C:\\Users\\gtrip\\OneDrive\\Desktop\\current\\frontend\\src\\App.jsx", "source_location": "L11", "weight": 1.0}, {"source": "c_users_gtrip_onedrive_desktop_current_frontend_src_app_jsx", "target": "c_users_gtrip_onedrive_desktop_current_frontend_src_components_horseloader", "relation": "imports_from", "confidence": "EXTRACTED", "source_file": "C:\\Users\\gtrip\\OneDrive\\Desktop\\current\\frontend\\src\\App.jsx", "source_location": "L12", "weight": 1.0}, {"source": "c_users_gtrip_onedrive_desktop_current_frontend_src_app_jsx", "target": "c_users_gtrip_onedrive_desktop_current_frontend_src_components_biasdashboard", "relation": "imports_from", "confidence": "EXTRACTED", "source_file": "C:\\Users\\gtrip\\OneDrive\\Desktop\\current\\frontend\\src\\App.jsx", "source_location": "L13", "weight": 1.0}, {"source": "c_users_gtrip_onedrive_desktop_current_frontend_src_app_jsx", "target": "c_users_gtrip_onedrive_desktop_current_frontend_src_components_talentpoolview", "relation": "imports_from", "confidence": "EXTRACTED", "source_file": "C:\\Users\\gtrip\\OneDrive\\Desktop\\current\\frontend\\src\\App.jsx", "source_location": "L14", "weight": 1.0}, {"source": "c_users_gtrip_onedrive_desktop_current_frontend_src_app_jsx", "target": "c_users_gtrip_onedrive_desktop_current_frontend_src_components_batchuploadview", "relation": "imports_from", "confidence": "EXTRACTED", "source_file": "C:\\Users\\gtrip\\OneDrive\\Desktop\\current\\frontend\\src\\App.jsx", "source_location": "L15", "weight": 1.0}, {"source": "c_users_gtrip_onedrive_desktop_current_frontend_src_app_jsx", "target": "c_users_gtrip_onedrive_desktop_current_frontend_src_components_authview", "relation": "imports_from", "confidence": "EXTRACTED", "source_file": "C:\\Users\\gtrip\\OneDrive\\Desktop\\current\\frontend\\src\\App.jsx", "source_location": "L16", "weight": 1.0}, {"source": "c_users_gtrip_onedrive_desktop_current_frontend_src_app_jsx", "target": "c_users_gtrip_onedrive_desktop_current_frontend_src_components_pipelinevisualizer", "relation": "imports_from", "confidence": "EXTRACTED", "source_file": "C:\\Users\\gtrip\\OneDrive\\Desktop\\current\\frontend\\src\\App.jsx", "source_location": "L17", "weight": 1.0}, {"source": "c_users_gtrip_onedrive_desktop_current_frontend_src_app_jsx", "target": "c_users_gtrip_onedrive_desktop_current_frontend_src_components_recruiterverificationmodal", "relation": "imports_from", "confidence": "EXTRACTED", "source_file": "C:\\Users\\gtrip\\OneDrive\\Desktop\\current\\frontend\\src\\App.jsx", "source_location": "L18", "weight": 1.0}, {"source": "c_users_gtrip_onedrive_desktop_current_frontend_src_app_jsx", "target": "c_users_gtrip_onedrive_desktop_current_frontend_src_context_authcontext", "relation": "imports_from", "confidence": "EXTRACTED", "source_file": "C:\\Users\\gtrip\\OneDrive\\Desktop\\current\\frontend\\src\\App.jsx", "source_location": "L19", "weight": 1.0}, {"source": "c_users_gtrip_onedrive_desktop_current_frontend_src_app_jsx", "target": "app_errorboundary", "relation": "contains", "confidence": "EXTRACTED", "source_file": "C:\\Users\\gtrip\\OneDrive\\Desktop\\current\\frontend\\src\\App.jsx", "source_location": "L21", "weight": 1.0}, {"source": "app_errorboundary", "target": "app_errorboundary_constructor", "relation": "method", "confidence": "EXTRACTED", "source_file": "C:\\Users\\gtrip\\OneDrive\\Desktop\\current\\frontend\\src\\App.jsx", "source_location": "L22", "weight": 1.0}, {"source": "app_errorboundary", "target": "app_errorboundary_getderivedstatefromerror", "relation": "method", "confidence": "EXTRACTED", "source_file": "C:\\Users\\gtrip\\OneDrive\\Desktop\\current\\frontend\\src\\App.jsx", "source_location": "L23", "weight": 1.0}, {"source": "app_errorboundary", "target": "app_errorboundary_render", "relation": "method", "confidence": "EXTRACTED", "source_file": "C:\\Users\\gtrip\\OneDrive\\Desktop\\current\\frontend\\src\\App.jsx", "source_location": "L24", "weight": 1.0}, {"source": "c_users_gtrip_onedrive_desktop_current_frontend_src_app_jsx", "target": "app_comingsoonnavitem", "relation": "contains", "confidence": "EXTRACTED", "source_file": "C:\\Users\\gtrip\\OneDrive\\Desktop\\current\\frontend\\src\\App.jsx", "source_location": "L39", "weight": 1.0}, {"source": "c_users_gtrip_onedrive_desktop_current_frontend_src_app_jsx", "target": "app_authmodal", "relation": "contains", "confidence": "EXTRACTED", "source_file": "C:\\Users\\gtrip\\OneDrive\\Desktop\\current\\frontend\\src\\App.jsx", "source_location": "L52", "weight": 1.0}, {"source": "c_users_gtrip_onedrive_desktop_current_frontend_src_app_jsx", "target": "app_useravatar", "relation": "contains", "confidence": "EXTRACTED", "source_file": "C:\\Users\\gtrip\\OneDrive\\Desktop\\current\\frontend\\src\\App.jsx", "source_location": "L90", "weight": 1.0}, {"source": "c_users_gtrip_onedrive_desktop_current_frontend_src_app_jsx", "target": "app_usermenu", "relation": "contains", "confidence": "EXTRACTED", "source_file": "C:\\Users\\gtrip\\OneDrive\\Desktop\\current\\frontend\\src\\App.jsx", "source_location": "L102", "weight": 1.0}, {"source": "c_users_gtrip_onedrive_desktop_current_frontend_src_app_jsx", "target": "app_publiclanding", "relation": "contains", "confidence": "EXTRACTED", "source_file": "C:\\Users\\gtrip\\OneDrive\\Desktop\\current\\frontend\\src\\App.jsx", "source_location": "L126", "weight": 1.0}, {"source": "c_users_gtrip_onedrive_desktop_current_frontend_src_app_jsx", "target": "app_authenticatedapp", "relation": "contains", "confidence": "EXTRACTED", "source_file": "C:\\Users\\gtrip\\OneDrive\\Desktop\\current\\frontend\\src\\App.jsx", "source_location": "L187", "weight": 1.0}, {"source": "c_users_gtrip_onedrive_desktop_current_frontend_src_app_jsx", "target": "app_app", "relation": "contains", "confidence": "EXTRACTED", "source_file": "C:\\Users\\gtrip\\OneDrive\\Desktop\\current\\frontend\\src\\App.jsx", "source_location": "L418", "weight": 1.0}], "raw_calls": [{"caller_nid": "app_errorboundary_constructor", "callee": "super", "source_file": "C:\\Users\\gtrip\\OneDrive\\Desktop\\current\\frontend\\src\\App.jsx", "source_location": "L22"}, {"caller_nid": "app_authmodal", "callee": "useEffect", "source_file": "C:\\Users\\gtrip\\OneDrive\\Desktop\\current\\frontend\\src\\App.jsx", "source_location": "L54"}, {"caller_nid": "app_useravatar", "callee": "toUpperCase", "source_file": "C:\\Users\\gtrip\\OneDrive\\Desktop\\current\\frontend\\src\\App.jsx", "source_location": "L92"}, {"caller_nid": "app_useravatar", "callee": "slice", "source_file": "C:\\Users\\gtrip\\OneDrive\\Desktop\\current\\frontend\\src\\App.jsx", "source_location": "L92"}, {"caller_nid": "app_useravatar", "callee": "join", "source_file": "C:\\Users\\gtrip\\OneDrive\\Desktop\\current\\frontend\\src\\App.jsx", "source_location": "L92"}, {"caller_nid": "app_useravatar", "callee": "map", "source_file": "C:\\Users\\gtrip\\OneDrive\\Desktop\\current\\frontend\\src\\App.jsx", "source_location": "L92"}, {"caller_nid": "app_useravatar", "callee": "split", "source_file": "C:\\Users\\gtrip\\OneDrive\\Desktop\\current\\frontend\\src\\App.jsx", "source_location": "L92"}, {"caller_nid": "app_authenticatedapp", "callee": "useAuth", "source_file": "C:\\Users\\gtrip\\OneDrive\\Desktop\\current\\frontend\\src\\App.jsx", "source_location": "L188"}, {"caller_nid": "app_authenticatedapp", "callee": "useState", "source_file": "C:\\Users\\gtrip\\OneDrive\\Desktop\\current\\frontend\\src\\App.jsx", "source_location": "L189"}, {"caller_nid": "app_authenticatedapp", "callee": "useState", "source_file": "C:\\Users\\gtrip\\OneDrive\\Desktop\\current\\frontend\\src\\App.jsx", "source_location": "L190"}, {"caller_nid": "app_authenticatedapp", "callee": "useState", "source_file": "C:\\Users\\gtrip\\OneDrive\\Desktop\\current\\frontend\\src\\App.jsx", "source_location": "L191"}, {"caller_nid": "app_authenticatedapp", "callee": "toUpperCase", "source_file": "C:\\Users\\gtrip\\OneDrive\\Desktop\\current\\frontend\\src\\App.jsx", "source_location": "L274"}, {"caller_nid": "app_authenticatedapp", "callee": "slice", "source_file": "C:\\Users\\gtrip\\OneDrive\\Desktop\\current\\frontend\\src\\App.jsx", "source_location": "L274"}, {"caller_nid": "app_authenticatedapp", "callee": "join", "source_file": "C:\\Users\\gtrip\\OneDrive\\Desktop\\current\\frontend\\src\\App.jsx", "source_location": "L274"}, {"caller_nid": "app_authenticatedapp", "callee": "map", "source_file": "C:\\Users\\gtrip\\OneDrive\\Desktop\\current\\frontend\\src\\App.jsx", "source_location": "L274"}, {"caller_nid": "app_authenticatedapp", "callee": "split", "source_file": "C:\\Users\\gtrip\\OneDrive\\Desktop\\current\\frontend\\src\\App.jsx", "source_location": "L274"}, {"caller_nid": "app_authenticatedapp", "callee": "(() => {\r\n            const activeStageIndex = Math.min(7, Math.floor((s.progress / 100) * 8));\r\n            return (\r\n              <div className=\"flex flex-col items-center justify-center min-h-[calc(100vh-3.5rem)] p-8 animate-fade-in\">\r\n                <h2 className=\"text-2xl font-bold text-white mb-2\">Analyzing Candidate Profile</h2>\r\n                <div className=\"text-white/60 mb-12 flex items-center gap-2\">\r\n                  <RefreshCw className=\"w-4 h-4 animate-spin text-emerald-400\" />\r\n                  Processing pipeline... {s.progress}%\r\n                </div>\r\n                \r\n                <div className=\"w-full max-w-4xl\">\r\n                  <PipelineVisualizer activeStageIndex={activeStageIndex} />\r\n                </div>\r\n                \r\n                <div className=\"w-full max-w-lg mt-6\">\r\n                  {/* Vertical Text Animation Container for logs (smaller footprint now) */}\r\n                  <div className=\"space-y-3 font-mono text-xs h-32 overflow-hidden relative glass-card p-4 rounded-xl border border-white/[0.08]\">\r\n                    {s.logs.filter(Boolean).map(log => (\r\n                      <div key={log.id} className={'flex items-start gap-3 animate-fade-in-up ' + getLogColor(log.type)}>\r\n                        <div className=\"mt-0.5\"><LogIcon type={log.type} /></div>\r\n                        <div className=\"leading-relaxed\">{log.text}</div>\r\n                      </div>\r\n                    ))}\r\n                    <div className=\"absolute bottom-0 left-0 right-0 h-16 bg-gradient-to-t from-[#0a0a0a] to-transparent pointer-events-none\" />\r\n                  </div>\r\n                </div>\r\n              </div>\r\n            );\r\n          })", "source_file": "C:\\Users\\gtrip\\OneDrive\\Desktop\\current\\frontend\\src\\App.jsx", "source_location": "L346"}, {"caller_nid": "app_app", "callee": "useAuth", "source_file": "C:\\Users\\gtrip\\OneDrive\\Desktop\\current\\frontend\\src\\App.jsx", "source_location": "L419"}, {"caller_nid": "app_app", "callee": "useAppState", "source_file": "C:\\Users\\gtrip\\OneDrive\\Desktop\\current\\frontend\\src\\App.jsx", "source_location": "L420"}, {"caller_nid": "app_app", "callee": "useState", "source_file": "C:\\Users\\gtrip\\OneDrive\\Desktop\\current\\frontend\\src\\App.jsx", "source_location": "L421"}, {"caller_nid": "app_app", "callee": "useState", "source_file": "C:\\Users\\gtrip\\OneDrive\\Desktop\\current\\frontend\\src\\App.jsx", "source_location": "L422"}, {"caller_nid": "app_app", "callee": "useRef", "source_file": "C:\\Users\\gtrip\\OneDrive\\Desktop\\current\\frontend\\src\\App.jsx", "source_location": "L425"}, {"caller_nid": "app_app", "callee": "useEffect", "source_file": "C:\\Users\\gtrip\\OneDrive\\Desktop\\current\\frontend\\src\\App.jsx", "source_location": "L426"}]}